lerobot/__init__.py
lerobot/__version__.py
lerobot/async_inference/configs.py
lerobot/async_inference/constants.py
lerobot/async_inference/helpers.py
lerobot/async_inference/policy_server.py
lerobot/async_inference/robot_client.py
lerobot/cameras/__init__.py
lerobot/cameras/camera.py
lerobot/cameras/configs.py
lerobot/cameras/utils.py
lerobot/cameras/opencv/__init__.py
lerobot/cameras/opencv/camera_opencv.py
lerobot/cameras/opencv/configuration_opencv.py
lerobot/cameras/reachy2_camera/__init__.py
lerobot/cameras/reachy2_camera/configuration_reachy2_camera.py
lerobot/cameras/reachy2_camera/reachy2_camera.py
lerobot/cameras/realsense/__init__.py
lerobot/cameras/realsense/camera_realsense.py
lerobot/cameras/realsense/configuration_realsense.py
lerobot/cameras/zmq/__init__.py
lerobot/cameras/zmq/camera_zmq.py
lerobot/cameras/zmq/configuration_zmq.py
lerobot/cameras/zmq/image_server.py
lerobot/configs/default.py
lerobot/configs/eval.py
lerobot/configs/parser.py
lerobot/configs/policies.py
lerobot/configs/train.py
lerobot/configs/types.py
lerobot/data_processing/__init__.py
lerobot/data_processing/sarm_annotations/__init__.py
lerobot/data_processing/sarm_annotations/subtask_annotation.py
lerobot/datasets/aggregate.py
lerobot/datasets/backward_compatibility.py
lerobot/datasets/card_template.md
lerobot/datasets/compute_stats.py
lerobot/datasets/dataset_tools.py
lerobot/datasets/factory.py
lerobot/datasets/image_writer.py
lerobot/datasets/lerobot_dataset.py
lerobot/datasets/online_buffer.py
lerobot/datasets/pipeline_features.py
lerobot/datasets/sampler.py
lerobot/datasets/streaming_dataset.py
lerobot/datasets/transforms.py
lerobot/datasets/utils.py
lerobot/datasets/video_utils.py
lerobot/datasets/push_dataset_to_hub/utils.py
lerobot/datasets/v30/augment_dataset_quantile_stats.py
lerobot/datasets/v30/convert_dataset_v21_to_v30.py
lerobot/envs/__init__.py
lerobot/envs/configs.py
lerobot/envs/factory.py
lerobot/envs/libero.py
lerobot/envs/metaworld.py
lerobot/envs/utils.py
lerobot_robodriver-0.4.3.dist-info/licenses/LICENSE
lerobot_robodriver-0.4.3.dist-info/METADATA
lerobot_robodriver-0.4.3.dist-info/WHEEL
lerobot_robodriver-0.4.3.dist-info/entry_points.txt
lerobot_robodriver-0.4.3.dist-info/top_level.txt
lerobot_robodriver-0.4.3.dist-info/RECORD
