Metadata-Version: 2.4
Name: lerobot-robodriver
Version: 0.4.3
Summary: 🤗 LeRobot: State-of-the-art Machine Learning for Real-World Robotics in Pytorch
Author-email: Rémi Cadène <re.cadene@gmail.com>, Simon Alibert <alibert.sim@gmail.com>, Alexander Soare <alexander.soare159@gmail.com>, Quentin Gallouédec <quentin.gallouedec@ec-lyon.fr>, Steven Palma <imstevenpmwork@ieee.org>, Pepijn Kooijmans <pepijnkooijmans@outlook.com>, Michel Aractingi <michel.aractingi@gmail.com>, Adil Zouitine <adilzouitinegm@gmail.com>, Dana Aubakirova <danaaubakirova17@gmail.com>, Caroline Pascal <caroline8.pascal@gmail.com>, Martino Russi <nopyeps@gmail.com>, Thomas W
License: Apache-2.0
Project-URL: homepage, https://huggingface.co/lerobot
Project-URL: documentation, https://huggingface.co/docs/lerobot/index
Project-URL: source, https://github.com/huggingface/lerobot
Project-URL: issues, https://github.com/huggingface/lerobot/issues
Project-URL: discord, https://discord.gg/s3KuuzsPFb
Keywords: lerobot,huggingface,robotics,machine learning,artificial intelligence
Classifier: Development Status :: 3 - Alpha
Classifier: Intended Audience :: Developers
Classifier: Intended Audience :: Education
Classifier: Intended Audience :: Science/Research
Classifier: License :: OSI Approved :: Apache Software License
Classifier: Programming Language :: Python :: 3.10
Classifier: Topic :: Software Development :: Build Tools
Classifier: Topic :: Scientific/Engineering :: Artificial Intelligence
Requires-Python: >=3.10
License-File: LICENSE
Requires-Dist: datasets<4.2.0,>=4.0.0
Requires-Dist: diffusers<0.36.0,>=0.27.2
Requires-Dist: huggingface-hub[cli,hf-transfer]<0.36.0,>=0.34.2
Requires-Dist: accelerate<2.0.0,>=1.10.0
Requires-Dist: setuptools<81.0.0,>=71.0.0
Requires-Dist: cmake<4.2.0,>=3.29.0.1
Requires-Dist: einops<0.9.0,>=0.8.0
Requires-Dist: opencv-python-headless<4.13.0,>=4.9.0
Requires-Dist: av<16.0.0,>=15.0.0
Requires-Dist: jsonlines<5.0.0,>=4.0.0
Requires-Dist: packaging<26.0,>=24.2
Requires-Dist: pynput<1.9.0,>=1.7.7
Requires-Dist: pyserial<4.0,>=3.5
Requires-Dist: wandb<0.22.0,>=0.20.0
Requires-Dist: torch<2.8.0,>=2.2.1
Requires-Dist: torchcodec<0.6.0,>=0.2.1; sys_platform != "win32" and (sys_platform != "linux" or (platform_machine != "aarch64" and platform_machine != "arm64" and platform_machine != "armv7l")) and (sys_platform != "darwin" or platform_machine != "x86_64")
Requires-Dist: torchvision<0.23.0,>=0.21.0
Requires-Dist: draccus==0.10.0
Requires-Dist: gymnasium<2.0.0,>=1.1.1
Requires-Dist: rerun-sdk<0.27.0,>=0.24.0
Requires-Dist: deepdiff<9.0.0,>=7.0.1
Requires-Dist: imageio[ffmpeg]<3.0.0,>=2.34.0
Requires-Dist: termcolor<4.0.0,>=2.4.0
Provides-Extra: pygame-dep
Requires-Dist: pygame<2.7.0,>=2.5.1; extra == "pygame-dep"
Provides-Extra: placo-dep
Requires-Dist: placo<0.10.0,>=0.9.6; extra == "placo-dep"
Provides-Extra: transformers-dep
Requires-Dist: transformers<5.0.0,>=4.57.1; extra == "transformers-dep"
Provides-Extra: grpcio-dep
Requires-Dist: grpcio==1.73.1; extra == "grpcio-dep"
Requires-Dist: protobuf==6.31.0; extra == "grpcio-dep"
Provides-Extra: feetech
Requires-Dist: feetech-servo-sdk<2.0.0,>=1.0.0; extra == "feetech"
Provides-Extra: dynamixel
Requires-Dist: dynamixel-sdk<3.9.0,>=3.7.31; extra == "dynamixel"
Provides-Extra: gamepad
Requires-Dist: lerobot[pygame-dep]; extra == "gamepad"
Requires-Dist: hidapi<0.15.0,>=0.14.0; extra == "gamepad"
Provides-Extra: hopejr
Requires-Dist: lerobot[feetech]; extra == "hopejr"
Requires-Dist: lerobot[pygame-dep]; extra == "hopejr"
Provides-Extra: lekiwi
Requires-Dist: lerobot[feetech]; extra == "lekiwi"
Requires-Dist: pyzmq<28.0.0,>=26.2.1; extra == "lekiwi"
Provides-Extra: unitree-g1
Requires-Dist: pyzmq<28.0.0,>=26.2.1; extra == "unitree-g1"
Requires-Dist: onnxruntime<2.0.0,>=1.16.0; extra == "unitree-g1"
Provides-Extra: reachy2
Requires-Dist: reachy2_sdk<1.1.0,>=1.0.15; extra == "reachy2"
Provides-Extra: kinematics
Requires-Dist: lerobot[placo-dep]; extra == "kinematics"
Provides-Extra: intelrealsense
Requires-Dist: pyrealsense2<2.57.0,>=2.55.1.6486; sys_platform != "darwin" and extra == "intelrealsense"
Requires-Dist: pyrealsense2-macosx<2.55.0,>=2.54; sys_platform == "darwin" and extra == "intelrealsense"
Provides-Extra: phone
Requires-Dist: hebi-py<2.12.0,>=2.8.0; extra == "phone"
Requires-Dist: teleop<0.2.0,>=0.1.0; extra == "phone"
Requires-Dist: fastapi<1.0; extra == "phone"
Provides-Extra: wallx
Requires-Dist: transformers==4.49.0; extra == "wallx"
Requires-Dist: peft==0.17.1; extra == "wallx"
Requires-Dist: scipy==1.15.3; extra == "wallx"
Requires-Dist: torchdiffeq==0.2.5; extra == "wallx"
Requires-Dist: qwen_vl_utils==0.0.11; extra == "wallx"
Provides-Extra: pi
Requires-Dist: transformers>=4.36.0; extra == "pi"
Requires-Dist: scipy<1.15,>=1.10.1; extra == "pi"
Provides-Extra: smolvla
Requires-Dist: lerobot[transformers-dep]; extra == "smolvla"
Requires-Dist: num2words<0.6.0,>=0.5.14; extra == "smolvla"
Requires-Dist: accelerate<2.0.0,>=1.7.0; extra == "smolvla"
Requires-Dist: safetensors<1.0.0,>=0.4.3; extra == "smolvla"
Provides-Extra: groot
Requires-Dist: lerobot[transformers-dep]; extra == "groot"
Requires-Dist: peft<1.0.0,>=0.13.0; extra == "groot"
Requires-Dist: dm-tree<1.0.0,>=0.1.8; extra == "groot"
Requires-Dist: timm<1.1.0,>=1.0.0; extra == "groot"
Requires-Dist: safetensors<1.0.0,>=0.4.3; extra == "groot"
Requires-Dist: Pillow<13.0.0,>=10.0.0; extra == "groot"
Requires-Dist: decord<1.0.0,>=0.6.0; (platform_machine == "AMD64" or platform_machine == "x86_64") and extra == "groot"
Requires-Dist: ninja<2.0.0,>=1.11.1; extra == "groot"
Requires-Dist: flash-attn<3.0.0,>=2.5.9; sys_platform != "darwin" and extra == "groot"
Provides-Extra: sarm
Requires-Dist: lerobot[transformers-dep]; extra == "sarm"
Requires-Dist: faker<35.0.0,>=33.0.0; extra == "sarm"
Requires-Dist: matplotlib<4.0.0,>=3.10.3; extra == "sarm"
Requires-Dist: qwen-vl-utils<0.1.0,>=0.0.14; extra == "sarm"
Provides-Extra: xvla
Requires-Dist: lerobot[transformers-dep]; extra == "xvla"
Provides-Extra: hilserl
Requires-Dist: lerobot[transformers-dep]; extra == "hilserl"
Requires-Dist: gym-hil<0.2.0,>=0.1.13; extra == "hilserl"
Requires-Dist: lerobot[grpcio-dep]; extra == "hilserl"
Requires-Dist: lerobot[placo-dep]; extra == "hilserl"
Provides-Extra: async
Requires-Dist: lerobot[grpcio-dep]; extra == "async"
Requires-Dist: matplotlib<4.0.0,>=3.10.3; extra == "async"
Provides-Extra: peft
Requires-Dist: lerobot[transformers-dep]; extra == "peft"
Requires-Dist: peft<1.0.0,>=0.18.0; extra == "peft"
Provides-Extra: dev
Requires-Dist: pre-commit<5.0.0,>=3.7.0; extra == "dev"
Requires-Dist: debugpy<1.9.0,>=1.8.1; extra == "dev"
Requires-Dist: lerobot[grpcio-dep]; extra == "dev"
Requires-Dist: grpcio-tools==1.73.1; extra == "dev"
Requires-Dist: mypy>=1.19.1; extra == "dev"
Provides-Extra: test
Requires-Dist: pytest<9.0.0,>=8.1.0; extra == "test"
Requires-Dist: pytest-timeout<3.0.0,>=2.4.0; extra == "test"
Requires-Dist: pytest-cov<8.0.0,>=5.0.0; extra == "test"
Requires-Dist: mock-serial<0.1.0,>=0.0.1; sys_platform != "win32" and extra == "test"
Provides-Extra: video-benchmark
Requires-Dist: scikit-image<0.26.0,>=0.23.2; extra == "video-benchmark"
Requires-Dist: pandas<2.4.0,>=2.2.2; extra == "video-benchmark"
Provides-Extra: aloha
Requires-Dist: gym-aloha<0.2.0,>=0.1.2; extra == "aloha"
Provides-Extra: pusht
Requires-Dist: gym-pusht<0.2.0,>=0.1.5; extra == "pusht"
Requires-Dist: pymunk<7.0.0,>=6.6.0; extra == "pusht"
Provides-Extra: libero
Requires-Dist: lerobot[transformers-dep]; extra == "libero"
Requires-Dist: hf-libero<0.2.0,>=0.1.3; extra == "libero"
Provides-Extra: metaworld
Requires-Dist: metaworld==3.0.0; extra == "metaworld"
Provides-Extra: all
Requires-Dist: lerobot[dynamixel]; extra == "all"
Requires-Dist: lerobot[gamepad]; extra == "all"
Requires-Dist: lerobot[hopejr]; extra == "all"
Requires-Dist: lerobot[lekiwi]; extra == "all"
Requires-Dist: lerobot[reachy2]; extra == "all"
Requires-Dist: lerobot[kinematics]; extra == "all"
Requires-Dist: lerobot[intelrealsense]; extra == "all"
Requires-Dist: lerobot[smolvla]; extra == "all"
Requires-Dist: lerobot[xvla]; extra == "all"
Requires-Dist: lerobot[hilserl]; extra == "all"
Requires-Dist: lerobot[async]; extra == "all"
Requires-Dist: lerobot[dev]; extra == "all"
Requires-Dist: lerobot[test]; extra == "all"
Requires-Dist: lerobot[video_benchmark]; extra == "all"
Requires-Dist: lerobot[aloha]; extra == "all"
Requires-Dist: lerobot[pusht]; extra == "all"
Requires-Dist: lerobot[phone]; extra == "all"
Requires-Dist: lerobot[libero]; extra == "all"
Requires-Dist: lerobot[metaworld]; extra == "all"
Requires-Dist: lerobot[sarm]; extra == "all"
Requires-Dist: lerobot[peft]; extra == "all"
Dynamic: description
Dynamic: description-content-type
Dynamic: license-file
